authproxy
