Metadata-Version: 1.0
Name: AuthProxy
Version: 0.1.0dev
Summary: middleware wsgi d authentification 
Home-page: UNKNOWN
Author: Laurent Tordjman
Author-email: cocoon.project@gmail.com
License: UNKNOWN
Platform: UNKNOWN
